CHANGES.txt
LICENSE.txt
MANIFEST.in
README.rst
development.ini
setup.cfg
setup.py
ringo/__init__.py
ringo/config.py
ringo/resources.py
ringo.egg-info/PKG-INFO
ringo.egg-info/SOURCES.txt
ringo.egg-info/dependency_links.txt
ringo.egg-info/entry_points.txt
ringo.egg-info/not-zip-safe
ringo.egg-info/requires.txt
ringo.egg-info/top_level.txt
ringo/alembic/alembic.ini
ringo/alembic/env.py
ringo/alembic/script.py.mako
ringo/alembic/versions/1a553ec2b34b_.py
ringo/alembic/versions/3520cf26d8d8_.py
ringo/alembic/versions/38eb5f63a8a4_.py
ringo/alembic/versions/4ff2bc4eb9bf_.py
ringo/alembic/versions/57c6ab33ad2f_.py
ringo/alembic/versions/99fda072ff9_.py
ringo/alembic/versions/ac95cbd0fce_.py
ringo/alembic/versions/cab8c02211c6_.py
ringo/lib/__init__.py
ringo/lib/alchemy.py
ringo/lib/cache.py
ringo/lib/extension.py
ringo/lib/form.py
ringo/lib/history.py
ringo/lib/i18n.py
ringo/lib/imexport.py
ringo/lib/message.py
ringo/lib/security.py
ringo/lib/sitetree.py
ringo/lib/table.py
ringo/lib/helpers/__init__.py
ringo/lib/helpers/appinfo.py
ringo/lib/helpers/format.py
ringo/lib/helpers/misc.py
ringo/lib/renderer/__init__.py
ringo/lib/renderer/dialogs.py
ringo/lib/renderer/form.py
ringo/lib/renderer/lists.py
ringo/lib/sql/__init__.py
ringo/lib/sql/cache.py
ringo/lib/sql/db.py
ringo/lib/sql/query.py
ringo/locale/ringo.pot
ringo/locale/de/LC_MESSAGES/ringo.po
ringo/locale/en/LC_MESSAGES/ringo.po
ringo/model/__init__.py
ringo/model/base.py
ringo/model/form.py
ringo/model/mixins.py
ringo/model/modul.py
ringo/model/statemachine.py
ringo/model/user.py
ringo/scaffolds/__init__.py
ringo/scaffolds/basic/CHANGES.txt
ringo/scaffolds/basic/MANIFEST.in_tmpl
ringo/scaffolds/basic/README.rst_tmpl
ringo/scaffolds/basic/development.ini_tmpl
ringo/scaffolds/basic/requirements.txt
ringo/scaffolds/basic/setup.cfg_tmpl
ringo/scaffolds/basic/setup.py_tmpl
ringo/scaffolds/basic/+package+/__init__.py_tmpl
ringo/scaffolds/basic/+package+/alembic/README
ringo/scaffolds/basic/+package+/alembic/alembic.ini_tmpl
ringo/scaffolds/basic/+package+/alembic/env.py_tmpl
ringo/scaffolds/basic/+package+/alembic/script.py.mako
ringo/scaffolds/basic/+package+/alembic/versions/README
