Metadata-Version: 1.1
Name: ringo
Version: 1.14.0
Summary: A simple web framework with base functionality to build web applications.
Home-page: https://bitbucket.org/ti/ringo
Author: Torsten Irländer
Author-email: torsten@irlaender.de
License: GNU General Public License v2 or later (GPLv2+)
Keywords: web wsgi bfg pylons pyramid
Platform: UNKNOWN
Classifier: Programming Language :: Python
Classifier: Framework :: Pyramid
Classifier: Topic :: Internet :: WWW/HTTP
Classifier: Topic :: Internet :: WWW/HTTP :: WSGI :: Application
Classifier: License :: OSI Approved :: GNU General Public License v2 or later (GPLv2+)
